[
  {
    "text": "the melon immediately",
    "intent": "clarify",
    "intent_prediction": {
      "name": "pick up",
      "confidence": 0.291420973357497
    }
  },
  {
    "text": "one brown lemon",
    "intent": "clarify",
    "intent_prediction": {
      "name": "pick up",
      "confidence": 0.41223201130646187
    }
  },
  {
    "text": "computer apple",
    "intent": "clarify",
    "intent_prediction": {
      "name": "find",
      "confidence": 0.34045127910461004
    }
  },
  {
    "text": "some yellow raspberry",
    "intent": "clarify",
    "intent_prediction": {
      "name": "pick up",
      "confidence": 0.4253595915212252
    }
  },
  {
    "text": "a box if you can",
    "intent": "clarify",
    "intent_prediction": {
      "name": "pick up",
      "confidence": 0.34931305689824005
    }
  },
  {
    "text": "i mean the ball which is magenta",
    "intent": "clarify",
    "intent_prediction": {
      "name": "show",
      "confidence": 0.2893317175299206
    }
  },
  {
    "text": "to the platform",
    "intent": "clarify",
    "intent_prediction": {
      "name": "move",
      "confidence": 0.41250081384406617
    }
  },
  {
    "text": "the orange one",
    "intent": "clarify",
    "intent_prediction": {
      "name": "find",
      "confidence": 0.27629268511770805
    }
  },
  {
    "text": "i mean on the middle",
    "intent": "clarify",
    "intent_prediction": {
      "name": "none",
      "confidence": 0.21244743166001592
    }
  },
  {
    "text": "it has the colour orange",
    "intent": "clarify",
    "intent_prediction": {
      "name": "show",
      "confidence": 0.2897776891727777
    }
  },
  {
    "text": "what i mean is one purple shape",
    "intent": "clarify",
    "intent_prediction": {
      "name": "show",
      "confidence": 0.3981187596573656
    }
  },
  {
    "text": "not the red apple i needed the orange",
    "intent": "clarify",
    "intent_prediction": {
      "name": "pick up",
      "confidence": 0.3659849966339406
    }
  },
  {
    "text": "middle",
    "intent": "clarify",
    "intent_prediction": {
      "name": "move",
      "confidence": 0.3137564738848628
    }
  },
  {
    "text": "that brown apple",
    "intent": "clarify",
    "intent_prediction": {
      "name": "pick up",
      "confidence": 0.5104889557484127
    }
  },
  {
    "text": "green",
    "intent": "clarify",
    "intent_prediction": {
      "name": "pick up",
      "confidence": 0.4714783209064657
    }
  },
  {
    "text": "the raspberry",
    "intent": "clarify",
    "intent_prediction": {
      "name": "pick up",
      "confidence": 0.31579148486448566
    }
  },
  {
    "text": "orange",
    "intent": "clarify",
    "intent_prediction": {
      "name": "pick up",
      "confidence": 0.39137161304921875
    }
  },
  {
    "text": "i mean some pineapple",
    "intent": "clarify",
    "intent_prediction": {
      "name": "pick up",
      "confidence": 0.279812831652656
    }
  },
  {
    "text": "an purple glass",
    "intent": "clarify",
    "intent_prediction": {
      "name": "pick up",
      "confidence": 0.4837709095593025
    }
  },
  {
    "text": "to the floor",
    "intent": "clarify",
    "intent_prediction": {
      "name": "move",
      "confidence": 0.3704723651482866
    }
  },
  {
    "text": "yellow",
    "intent": "clarify",
    "intent_prediction": {
      "name": "find",
      "confidence": 0.3213496921018251
    }
  },
  {
    "text": "this pizza which is green if you can",
    "intent": "clarify",
    "intent_prediction": {
      "name": "show",
      "confidence": 0.3919465142317126
    }
  },
  {
    "text": "placed in the ground area",
    "intent": "clarify",
    "intent_prediction": {
      "name": "move",
      "confidence": 0.3814531780902727
    }
  },
  {
    "text": "some yellow shape if you can",
    "intent": "clarify",
    "intent_prediction": {
      "name": "pick up",
      "confidence": 0.4287886865335395
    }
  },
  {
    "text": "the green apple",
    "intent": "clarify",
    "intent_prediction": {
      "name": "pick up",
      "confidence": 0.3487921559194189
    }
  },
  {
    "text": "the brick",
    "intent": "clarify",
    "intent_prediction": {
      "name": "pick up",
      "confidence": 0.267849927850975
    }
  },
  {
    "text": "i meant on the platform",
    "intent": "clarify",
    "intent_prediction": {
      "name": "move",
      "confidence": 0.23933542046155326
    }
  },
  {
    "text": "dear robert try again byt now at littel more to your left",
    "intent": "clarify",
    "intent_prediction": {
      "name": "none",
      "confidence": 0.1407307384619638
    }
  },
  {
    "text": "i want you to look for a bracelet in the middle",
    "intent": "find",
    "intent_prediction": {
      "name": "show",
      "confidence": 0.20186036565151225
    }
  },
  {
    "text": "what i meant was find this shape which is brown maybe",
    "intent": "find",
    "intent_prediction": {
      "name": "show",
      "confidence": 0.3428542481942528
    }
  },
  {
    "text": "immediately i'm asking you to find the orange pineapple if you can",
    "intent": "find",
    "intent_prediction": {
      "name": "pick up",
      "confidence": 0.28538253638459626
    }
  },
  {
    "text": "ok also find an lemon which is magenta if you can",
    "intent": "find",
    "intent_prediction": {
      "name": "show",
      "confidence": 0.2644481346821933
    }
  },
  {
    "text": "stop the object is not correct find the yellow grapes which is a long curved fruit with smooth skin",
    "intent": "find",
    "intent_prediction": {
      "name": "show",
      "confidence": 0.3895635703668986
    }
  },
  {
    "text": "identify the yellow duck by showing it with your arm",
    "intent": "find",
    "intent_prediction": {
      "name": "show",
      "confidence": 0.2674253878052481
    }
  },
  {
    "text": "show me the yellow duck",
    "intent": "find",
    "intent_prediction": {
      "name": "show",
      "confidence": 0.28545587798261823
    }
  },
  {
    "text": "somehow can you pinpoint watermelon that has a purple color also",
    "intent": "find",
    "intent_prediction": {
      "name": "show",
      "confidence": 0.3541094075759742
    }
  },
  {
    "text": "identify the hammer made out of wood",
    "intent": "find",
    "intent_prediction": {
      "name": "pick up",
      "confidence": 0.2609602013755855
    }
  },
  {
    "text": "do you recognize a bracelet on the table",
    "intent": "find",
    "intent_prediction": {
      "name": "show",
      "confidence": 0.28311393602236146
    }
  },
  {
    "text": "can you see the cherry",
    "intent": "find",
    "intent_prediction": {
      "name": "pick up",
      "confidence": 0.23049929206369626
    }
  },
  {
    "text": "now find something else",
    "intent": "find",
    "intent_prediction": {
      "name": "show",
      "confidence": 0.3601501327468041
    }
  },
  {
    "text": "where is raspberry which has the color brown",
    "intent": "find",
    "intent_prediction": {
      "name": "show",
      "confidence": 0.3227215475286688
    }
  },
  {
    "text": "ok find this brown tool if possible",
    "intent": "find",
    "intent_prediction": {
      "name": "show",
      "confidence": 0.251535017725858
    }
  },
  {
    "text": "ok somehow recognize an yellow tomato thanks",
    "intent": "find",
    "intent_prediction": {
      "name": "pick up",
      "confidence": 0.24130352617345935
    }
  },
  {
    "text": "maybe can you identify this black ball if possible",
    "intent": "find",
    "intent_prediction": {
      "name": "pick up",
      "confidence": 0.27574836605317093
    }
  },
  {
    "text": "find something",
    "intent": "find",
    "intent_prediction": {
      "name": "show",
      "confidence": 0.3154522592322567
    }
  },
  {
    "text": "now i want you to look for a brown apple",
    "intent": "find",
    "intent_prediction": {
      "name": "pick up",
      "confidence": 0.3385641196864796
    }
  },
  {
    "text": "um look for the object if you can",
    "intent": "find",
    "intent_prediction": {
      "name": "show",
      "confidence": 0.2877621284245496
    }
  },
  {
    "text": "drop that brown glass to somewhere on the middle",
    "intent": "move",
    "intent_prediction": {
      "name": "pick up",
      "confidence": 0.3344830505870281
    }
  },
  {
    "text": "i want you to move this ball to the right",
    "intent": "move",
    "intent_prediction": {
      "name": "pick up",
      "confidence": 0.40100629932484183
    }
  },
  {
    "text": "what i mean is snatch this magenta raspberry positioned in the right area afterwards relocate that to the ground",
    "intent": "move",
    "intent_prediction": {
      "name": "pick up",
      "confidence": 0.2514307197630149
    }
  },
  {
    "text": "put this object on the right",
    "intent": "move",
    "intent_prediction": {
      "name": "show",
      "confidence": 0.31557839575876634
    }
  },
  {
    "text": "i really really really want you to throw the ball to the left",
    "intent": "move",
    "intent_prediction": {
      "name": "pick up",
      "confidence": 0.3212807753623758
    }
  },
  {
    "text": "drop that apricot that has a green color towards the middle side",
    "intent": "move",
    "intent_prediction": {
      "name": "pick up",
      "confidence": 0.28293446079253054
    }
  },
  {
    "text": "throw the banana to the floor",
    "intent": "move",
    "intent_prediction": {
      "name": "pick up",
      "confidence": 0.5586994515442498
    }
  },
  {
    "text": "toss the orange ball",
    "intent": "move",
    "intent_prediction": {
      "name": "pick up",
      "confidence": 0.5874766081144863
    }
  },
  {
    "text": "could you move this object to the left please",
    "intent": "move",
    "intent_prediction": {
      "name": "pick up",
      "confidence": 0.2764646592761102
    }
  },
  {
    "text": "place the orange of color blue towards the platform side",
    "intent": "move",
    "intent_prediction": {
      "name": "find",
      "confidence": 0.3155424164357848
    }
  },
  {
    "text": "move the banana to a basket near the table",
    "intent": "move",
    "intent_prediction": {
      "name": "pick up",
      "confidence": 0.3457123629763024
    }
  },
  {
    "text": "move this thing and put it there",
    "intent": "move",
    "intent_prediction": {
      "name": "none",
      "confidence": 0.1907601387557567
    }
  },
  {
    "text": "can you pick this up first and after that please put it over there",
    "intent": "move",
    "intent_prediction": {
      "name": "pick up",
      "confidence": 0.22010537835651187
    }
  },
  {
    "text": "throw out the orange ball",
    "intent": "move",
    "intent_prediction": {
      "name": "pick up",
      "confidence": 0.6201303826792539
    }
  },
  {
    "text": "somehow i want you to detect a yellow hammer somewhere on the platform afterwards move it towards the ground side",
    "intent": "move",
    "intent_prediction": {
      "name": "pick up",
      "confidence": 0.295210934906625
    }
  },
  {
    "text": "drag an end-effector to the object",
    "intent": "pick up",
    "intent_prediction": {
      "name": "show",
      "confidence": 0.2674693546178608
    }
  },
  {
    "text": "what i meant was get some donut which is magenta thanks",
    "intent": "pick up",
    "intent_prediction": {
      "name": "show",
      "confidence": 0.2532614491244752
    }
  },
  {
    "text": "acquire an blue melon at the table",
    "intent": "pick up",
    "intent_prediction": {
      "name": "find",
      "confidence": 0.3133691681732014
    }
  },
  {
    "text": "what i meant was put this magenta shape",
    "intent": "pick up",
    "intent_prediction": {
      "name": "show",
      "confidence": 0.25128692409903186
    }
  },
  {
    "text": "hey could you place the apple on the left",
    "intent": "pick up",
    "intent_prediction": {
      "name": "move",
      "confidence": 0.24617207701451274
    }
  },
  {
    "text": "i mean put a pineapple which has a black color located in the area on the ground",
    "intent": "pick up",
    "intent_prediction": {
      "name": "show",
      "confidence": 0.3116909184551994
    }
  },
  {
    "text": "hold on to the ball",
    "intent": "pick up",
    "intent_prediction": {
      "name": "move",
      "confidence": 0.3240422748783406
    }
  },
  {
    "text": "point at the green apricot",
    "intent": "pick up",
    "intent_prediction": {
      "name": "find",
      "confidence": 0.26254952987628527
    }
  },
  {
    "text": "grab a pink duck in the area on the center",
    "intent": "pick up",
    "intent_prediction": {
      "name": "find",
      "confidence": 0.2764387181936828
    }
  },
  {
    "text": "grab the object in front of you",
    "intent": "pick up",
    "intent_prediction": {
      "name": "show",
      "confidence": 0.23587841415110727
    }
  },
  {
    "text": "the orange banana which is in the middle area",
    "intent": "pick up",
    "intent_prediction": {
      "name": "show",
      "confidence": 0.31289977784002576
    }
  },
  {
    "text": "learn the green apple in the middle of the table",
    "intent": "show",
    "intent_prediction": {
      "name": "find",
      "confidence": 0.28854218882122806
    }
  },
  {
    "text": "learn sliver can",
    "intent": "show",
    "intent_prediction": {
      "name": "find",
      "confidence": 0.29409157757184534
    }
  },
  {
    "text": "save this white can",
    "intent": "show",
    "intent_prediction": {
      "name": "pick up",
      "confidence": 0.27643071044835454
    }
  },
  {
    "text": "please inspect the new item",
    "intent": "show",
    "intent_prediction": {
      "name": "find",
      "confidence": 0.2391979671854034
    }
  },
  {
    "text": "save this object's name and characteristics on your library",
    "intent": "show",
    "intent_prediction": {
      "name": "none",
      "confidence": 0.3008429616186962
    }
  },
  {
    "text": "a 3 inches plastic object black or grey clicks when pressed = computer control",
    "intent": "show",
    "intent_prediction": {
      "name": "pick up",
      "confidence": 0.44329521907228125
    }
  },
  {
    "text": "check this pink triangle very slowly",
    "intent": "show",
    "intent_prediction": {
      "name": "find",
      "confidence": 0.25615025177268175
    }
  },
  {
    "text": "save into your hard drive",
    "intent": "show",
    "intent_prediction": {
      "name": "pick up",
      "confidence": 0.2755623142114874
    }
  },
  {
    "text": "a pear is called the pink lemon",
    "intent": "show",
    "intent_prediction": {
      "name": "find",
      "confidence": 0.28148335631637533
    }
  },
  {
    "text": "learn white bottle",
    "intent": "show",
    "intent_prediction": {
      "name": "pick up",
      "confidence": 0.35945141745178333
    }
  },
  {
    "text": "register as grey bottle",
    "intent": "show",
    "intent_prediction": {
      "name": "pick up",
      "confidence": 0.5075679981658614
    }
  },
  {
    "text": "hi what's up dummy boy",
    "intent": "greetings",
    "intent_prediction": {
      "name": "none",
      "confidence": 0.21790472428939328
    }
  },
  {
    "text": "good morning robot",
    "intent": "greetings",
    "intent_prediction": {
      "name": "show",
      "confidence": 0.19166104792343489
    }
  },
  {
    "text": "hey how you doing",
    "intent": "greetings",
    "intent_prediction": {
      "name": "deny",
      "confidence": 0.29095130058991764
    }
  },
  {
    "text": "hello what is your name are you ready to work for me",
    "intent": "greetings",
    "intent_prediction": {
      "name": "none",
      "confidence": 0.24869494147015406
    }
  },
  {
    "text": "hello is anybody there",
    "intent": "greetings",
    "intent_prediction": {
      "name": "affirmative",
      "confidence": 0.16242957809978836
    }
  },
  {
    "text": "hallo build me something",
    "intent": "greetings",
    "intent_prediction": {
      "name": "pick up",
      "confidence": 0.21942147835847517
    }
  },
  {
    "text": "yeah that's what i told you",
    "intent": "affirmative",
    "intent_prediction": {
      "name": "none",
      "confidence": 0.2728451679840156
    }
  },
  {
    "text": "that's correct",
    "intent": "affirmative",
    "intent_prediction": {
      "name": "none",
      "confidence": 0.3320882658925368
    }
  },
  {
    "text": "all right",
    "intent": "affirmative",
    "intent_prediction": {
      "name": "none",
      "confidence": 0.2666511402347451
    }
  },
  {
    "text": "yes it is correct",
    "intent": "affirmative",
    "intent_prediction": {
      "name": "deny",
      "confidence": 0.37312317835194186
    }
  },
  {
    "text": "yes it is",
    "intent": "affirmative",
    "intent_prediction": {
      "name": "deny",
      "confidence": 0.28597161860032805
    }
  },
  {
    "text": "that s okay",
    "intent": "affirmative",
    "intent_prediction": {
      "name": "none",
      "confidence": 0.25114220433552437
    }
  },
  {
    "text": "yes pick it up",
    "intent": "affirmative",
    "intent_prediction": {
      "name": "pick up",
      "confidence": 0.3405099638974458
    }
  },
  {
    "text": "yeah that's right",
    "intent": "affirmative",
    "intent_prediction": {
      "name": "none",
      "confidence": 0.24749895607274966
    }
  },
  {
    "text": "i don't mind",
    "intent": "affirmative",
    "intent_prediction": {
      "name": "none",
      "confidence": 0.3434799367574607
    }
  },
  {
    "text": "yeah that's what i want",
    "intent": "affirmative",
    "intent_prediction": {
      "name": "none",
      "confidence": 0.3147118374582003
    }
  },
  {
    "text": "yeah pick it up like i said",
    "intent": "affirmative",
    "intent_prediction": {
      "name": "deny",
      "confidence": 0.20034692791746442
    }
  },
  {
    "text": "yes that's what i want",
    "intent": "affirmative",
    "intent_prediction": {
      "name": "none",
      "confidence": 0.33440311366536635
    }
  },
  {
    "text": "hey alexa play rock music",
    "intent": "none",
    "intent_prediction": {
      "name": "greetings",
      "confidence": 0.31907694477772547
    }
  },
  {
    "text": "can you play with me",
    "intent": "none",
    "intent_prediction": {
      "name": "pick up",
      "confidence": 0.24080539519290312
    }
  },
  {
    "text": "which item do you want to smash first",
    "intent": "none",
    "intent_prediction": {
      "name": "pick up",
      "confidence": 0.29552741414982625
    }
  },
  {
    "text": "what date is it today",
    "intent": "none",
    "intent_prediction": {
      "name": "deny",
      "confidence": 0.282406415741581
    }
  },
  {
    "text": "leave me alone",
    "intent": "none",
    "intent_prediction": {
      "name": "pick up",
      "confidence": 0.23011874976253718
    }
  },
  {
    "text": "too bad",
    "intent": "none",
    "intent_prediction": {
      "name": "deny",
      "confidence": 0.3471104423110625
    }
  },
  {
    "text": "strangle yourself with your arms",
    "intent": "none",
    "intent_prediction": {
      "name": "pick up",
      "confidence": 0.49935319392276983
    }
  },
  {
    "text": "seriously tell me what you can do",
    "intent": "none",
    "intent_prediction": {
      "name": "deny",
      "confidence": 0.24790916357430076
    }
  },
  {
    "text": "i like you",
    "intent": "none",
    "intent_prediction": {
      "name": "deny",
      "confidence": 0.1986469467866858
    }
  },
  {
    "text": "why",
    "intent": "none",
    "intent_prediction": {
      "name": "deny",
      "confidence": 0.3301493053469038
    }
  },
  {
    "text": "by showing it the right thing to do",
    "intent": "none",
    "intent_prediction": {
      "name": "show",
      "confidence": 0.2084336540128174
    }
  },
  {
    "text": ":)",
    "intent": "none",
    "intent_prediction": {
      "name": "affirmative",
      "confidence": 0.46350778385255953
    }
  },
  {
    "text": "what are you a gallagher bot",
    "intent": "none",
    "intent_prediction": {
      "name": "show",
      "confidence": 0.29243327422437687
    }
  },
  {
    "text": "fuck your shiny metal ass",
    "intent": "none",
    "intent_prediction": {
      "name": "pick up",
      "confidence": 0.2940887984775005
    }
  },
  {
    "text": "silver top curved 2 to 3 inches long 1 to 2 inches wide light weight",
    "intent": "none",
    "intent_prediction": {
      "name": "pick up",
      "confidence": 0.5697848793431772
    }
  },
  {
    "text": "i'm confused",
    "intent": "none",
    "intent_prediction": {
      "name": "deny",
      "confidence": 0.473544555367333
    }
  },
  {
    "text": "can you try it with your right arm this time",
    "intent": "none",
    "intent_prediction": {
      "name": "pick up",
      "confidence": 0.32145394073877054
    }
  },
  {
    "text": "okay thank you bye",
    "intent": "bye",
    "intent_prediction": {
      "name": "affirmative",
      "confidence": 0.40251793321991064
    }
  },
  {
    "text": "bye bye take care",
    "intent": "bye",
    "intent_prediction": {
      "name": "affirmative",
      "confidence": 0.25843655717074876
    }
  },
  {
    "text": "bye then",
    "intent": "bye",
    "intent_prediction": {
      "name": "affirmative",
      "confidence": 0.24379601861476977
    }
  },
  {
    "text": "that's all for now bye robot",
    "intent": "bye",
    "intent_prediction": {
      "name": "none",
      "confidence": 0.2755235167188561
    }
  },
  {
    "text": "we'll speak soon",
    "intent": "bye",
    "intent_prediction": {
      "name": "none",
      "confidence": 0.256111342278071
    }
  },
  {
    "text": "thanks bye bye",
    "intent": "bye",
    "intent_prediction": {
      "name": "greetings",
      "confidence": 0.34879286102113294
    }
  },
  {
    "text": "see ya",
    "intent": "bye",
    "intent_prediction": {
      "name": "affirmative",
      "confidence": 0.32023097172778897
    }
  },
  {
    "text": "ok bye then",
    "intent": "bye",
    "intent_prediction": {
      "name": "affirmative",
      "confidence": 0.41934094131865823
    }
  },
  {
    "text": "i don't wanna do this bye",
    "intent": "bye",
    "intent_prediction": {
      "name": "none",
      "confidence": 0.25904061011679597
    }
  },
  {
    "text": "ok bye",
    "intent": "bye",
    "intent_prediction": {
      "name": "affirmative",
      "confidence": 0.45752747767169427
    }
  },
  {
    "text": "that's wrong",
    "intent": "deny",
    "intent_prediction": {
      "name": "none",
      "confidence": 0.34061644796609997
    }
  },
  {
    "text": "no i wanted you to",
    "intent": "deny",
    "intent_prediction": {
      "name": "none",
      "confidence": 0.26268454152445275
    }
  },
  {
    "text": "no don't do that",
    "intent": "deny",
    "intent_prediction": {
      "name": "none",
      "confidence": 0.36814183766666025
    }
  },
  {
    "text": "emergency button",
    "intent": "deny",
    "intent_prediction": {
      "name": "find",
      "confidence": 0.3120764877227898
    }
  },
  {
    "text": "just forget about it",
    "intent": "deny",
    "intent_prediction": {
      "name": "none",
      "confidence": 0.22769253757749075
    }
  },
  {
    "text": "no you didn't understand",
    "intent": "deny",
    "intent_prediction": {
      "name": "none",
      "confidence": 0.34096007289595043
    }
  },
  {
    "text": "dont mean that",
    "intent": "deny",
    "intent_prediction": {
      "name": "none",
      "confidence": 0.3643286879692973
    }
  },
  {
    "text": "that's not right",
    "intent": "deny",
    "intent_prediction": {
      "name": "none",
      "confidence": 0.28693631015964455
    }
  },
  {
    "text": "that's not what i meant",
    "intent": "deny",
    "intent_prediction": {
      "name": "none",
      "confidence": 0.34952468282046006
    }
  },
  {
    "text": "i didn't ask for that",
    "intent": "deny",
    "intent_prediction": {
      "name": "none",
      "confidence": 0.41045375283761937
    }
  }
]