[
  {
    "text": "spot the pink orange on the floor side",
    "entities": [
      {
        "start": 9,
        "end": 13,
        "value": "pink",
        "entity": "object_color"
      },
      {
        "start": 14,
        "end": 20,
        "value": "orange",
        "entity": "object_name"
      },
      {
        "start": 28,
        "end": 33,
        "value": "floor",
        "entity": "placement"
      }
    ],
    "predicted_entities": [
      {
        "entity": "object_color",
        "value": "pink",
        "start": 9,
        "end": 13,
        "confidence": null,
        "extractor": "MitieEntityExtractor"
      },
      {
        "entity": "object_color",
        "value": "orange",
        "start": 14,
        "end": 20,
        "confidence": null,
        "extractor": "MitieEntityExtractor"
      },
      {
        "entity": "placement",
        "value": "floor",
        "start": 28,
        "end": 33,
        "confidence": null,
        "extractor": "MitieEntityExtractor"
      }
    ]
  },
  {
    "text": "lastly please search for something red",
    "entities": [
      {
        "start": 35,
        "end": 38,
        "value": "red",
        "entity": "object_color"
      }
    ],
    "predicted_entities": [
      {
        "entity": "object_color",
        "value": "lastly",
        "start": 0,
        "end": 6,
        "confidence": null,
        "extractor": "MitieEntityExtractor"
      },
      {
        "entity": "object_color",
        "value": "red",
        "start": 35,
        "end": 38,
        "confidence": null,
        "extractor": "MitieEntityExtractor"
      }
    ]
  },
  {
    "text": "grab the cup lift it and put it here",
    "entities": [
      {
        "start": 9,
        "end": 12,
        "value": "cup",
        "entity": "object_name"
      }
    ],
    "predicted_entities": [
      {
        "entity": "object_name",
        "value": "cup",
        "start": 9,
        "end": 12,
        "confidence": null,
        "extractor": "MitieEntityExtractor"
      },
      {
        "entity": "placement",
        "value": "here",
        "start": 32,
        "end": 36,
        "confidence": null,
        "extractor": "MitieEntityExtractor"
      }
    ]
  },
  {
    "text": "please take the red ball with your gripper and when you're done put it in the bottom left corner",
    "entities": [
      {
        "start": 16,
        "end": 19,
        "value": "red",
        "entity": "object_color"
      },
      {
        "start": 20,
        "end": 24,
        "value": "ball",
        "entity": "object_name"
      },
      {
        "start": 78,
        "end": 89,
        "value": "bottom left",
        "entity": "placement"
      }
    ],
    "predicted_entities": [
      {
        "entity": "object_color",
        "value": "red",
        "start": 16,
        "end": 19,
        "confidence": null,
        "extractor": "MitieEntityExtractor"
      },
      {
        "entity": "object_name",
        "value": "ball",
        "start": 20,
        "end": 24,
        "confidence": null,
        "extractor": "MitieEntityExtractor"
      },
      {
        "entity": "placement",
        "value": "bottom left corner",
        "start": 78,
        "end": 96,
        "confidence": null,
        "extractor": "MitieEntityExtractor"
      }
    ]
  },
  {
    "text": "could you move the orange block",
    "entities": [
      {
        "start": 19,
        "end": 25,
        "value": "orange",
        "entity": "object_color"
      },
      {
        "start": 26,
        "end": 31,
        "value": "block",
        "entity": "object_name"
      }
    ],
    "predicted_entities": [
      {
        "entity": "object_color",
        "value": "orange",
        "start": 19,
        "end": 25,
        "confidence": null,
        "extractor": "MitieEntityExtractor"
      }
    ]
  },
  {
    "text": "i'm asking you to hold the teddy bear",
    "entities": [
      {
        "start": 27,
        "end": 37,
        "value": "teddy bear",
        "entity": "object_name"
      }
    ],
    "predicted_entities": [
      {
        "entity": "object_name",
        "value": "teddy",
        "start": 27,
        "end": 32,
        "confidence": null,
        "extractor": "MitieEntityExtractor"
      }
    ]
  },
  {
    "text": "i want you to clasp this thing",
    "entities": [
      {
        "start": 25,
        "end": 30,
        "value": "thing",
        "entity": "object_name"
      }
    ],
    "predicted_entities": [
      {
        "entity": "object_name",
        "value": "clasp",
        "start": 14,
        "end": 19,
        "confidence": null,
        "extractor": "MitieEntityExtractor"
      },
      {
        "entity": "object_name",
        "value": "thing",
        "start": 25,
        "end": 30,
        "confidence": null,
        "extractor": "MitieEntityExtractor"
      }
    ]
  },
  {
    "text": "could you grab the gray can from the center of the platform",
    "entities": [
      {
        "start": 19,
        "end": 23,
        "value": "gray",
        "entity": "object_color"
      },
      {
        "start": 24,
        "end": 27,
        "value": "can",
        "entity": "object_name"
      },
      {
        "start": 37,
        "end": 43,
        "value": "center",
        "entity": "placement"
      }
    ],
    "predicted_entities": [
      {
        "entity": "object_name",
        "value": "gray",
        "start": 19,
        "end": 23,
        "confidence": null,
        "extractor": "MitieEntityExtractor"
      },
      {
        "entity": "placement",
        "value": "center",
        "start": 37,
        "end": 43,
        "confidence": null,
        "extractor": "MitieEntityExtractor"
      }
    ]
  },
  {
    "text": "hand over that cup over there",
    "entities": [
      {
        "start": 15,
        "end": 18,
        "value": "cup",
        "entity": "object_name"
      }
    ],
    "predicted_entities": [
      {
        "entity": "object_name",
        "value": "that cup",
        "start": 10,
        "end": 18,
        "confidence": null,
        "extractor": "MitieEntityExtractor"
      }
    ]
  },
  {
    "text": "i want you to learn a new object",
    "entities": [
      {
        "start": 26,
        "end": 32,
        "value": "object",
        "entity": "object_name"
      }
    ],
    "predicted_entities": [
      {
        "entity": "object_color",
        "value": "new",
        "start": 22,
        "end": 25,
        "confidence": null,
        "extractor": "MitieEntityExtractor"
      },
      {
        "entity": "object_name",
        "value": "object",
        "start": 26,
        "end": 32,
        "confidence": null,
        "extractor": "MitieEntityExtractor"
      }
    ]
  },
  {
    "text": "here is a fruit with a yellow color",
    "entities": [
      {
        "start": 10,
        "end": 15,
        "value": "fruit",
        "entity": "object_name"
      },
      {
        "start": 23,
        "end": 29,
        "value": "yellow",
        "entity": "object_color"
      }
    ],
    "predicted_entities": [
      {
        "entity": "object_name",
        "value": "fruit",
        "start": 10,
        "end": 15,
        "confidence": null,
        "extractor": "MitieEntityExtractor"
      },
      {
        "entity": "object_name",
        "value": "with",
        "start": 16,
        "end": 20,
        "confidence": null,
        "extractor": "MitieEntityExtractor"
      },
      {
        "entity": "object_color",
        "value": "yellow",
        "start": 23,
        "end": 29,
        "confidence": null,
        "extractor": "MitieEntityExtractor"
      }
    ]
  },
  {
    "text": "this object is a kiwi",
    "entities": [
      {
        "start": 17,
        "end": 21,
        "value": "kiwi",
        "entity": "object_name"
      }
    ],
    "predicted_entities": [
      {
        "entity": "object_name",
        "value": "object",
        "start": 5,
        "end": 11,
        "confidence": null,
        "extractor": "MitieEntityExtractor"
      },
      {
        "entity": "object_name",
        "value": "kiwi",
        "start": 17,
        "end": 21,
        "confidence": null,
        "extractor": "MitieEntityExtractor"
      }
    ]
  },
  {
    "text": "hello fellow human",
    "entities": [],
    "predicted_entities": [
      {
        "entity": "object_color",
        "value": "fellow",
        "start": 6,
        "end": 12,
        "confidence": null,
        "extractor": "MitieEntityExtractor"
      },
      {
        "entity": "object_name",
        "value": "human",
        "start": 13,
        "end": 18,
        "confidence": null,
        "extractor": "MitieEntityExtractor"
      }
    ]
  },
  {
    "text": "howdy pal",
    "entities": [],
    "predicted_entities": [
      {
        "entity": "object_name",
        "value": "pal",
        "start": 6,
        "end": 9,
        "confidence": null,
        "extractor": "MitieEntityExtractor"
      }
    ]
  },
  {
    "text": "whats up",
    "entities": [],
    "predicted_entities": [
      {
        "entity": "object_color",
        "value": "whats",
        "start": 0,
        "end": 5,
        "confidence": null,
        "extractor": "MitieEntityExtractor"
      }
    ]
  },
  {
    "text": "hello is anybody there",
    "entities": [],
    "predicted_entities": [
      {
        "entity": "object_name",
        "value": "there",
        "start": 17,
        "end": 22,
        "confidence": null,
        "extractor": "MitieEntityExtractor"
      }
    ]
  },
  {
    "text": "let's have a discussion",
    "entities": [],
    "predicted_entities": [
      {
        "entity": "object_name",
        "value": "discussion",
        "start": 13,
        "end": 23,
        "confidence": null,
        "extractor": "MitieEntityExtractor"
      }
    ]
  },
  {
    "text": "let's discuss something",
    "entities": [],
    "predicted_entities": [
      {
        "entity": "object_name",
        "value": "something",
        "start": 14,
        "end": 23,
        "confidence": null,
        "extractor": "MitieEntityExtractor"
      }
    ]
  },
  {
    "text": "long time no see",
    "entities": [],
    "predicted_entities": [
      {
        "entity": "object_name",
        "value": "time",
        "start": 5,
        "end": 9,
        "confidence": null,
        "extractor": "MitieEntityExtractor"
      }
    ]
  },
  {
    "text": "cancel the whole thing",
    "entities": [],
    "predicted_entities": [
      {
        "entity": "object_color",
        "value": "whole",
        "start": 11,
        "end": 16,
        "confidence": null,
        "extractor": "MitieEntityExtractor"
      }
    ]
  }
]