[
  {
    "text": "towards the ground zone",
    "intent": "clarify",
    "intent_prediction": {
      "name": "move",
      "confidence": 0.9432801008224487
    }
  },
  {
    "text": "the apple is green",
    "intent": "clarify",
    "intent_prediction": {
      "name": "show",
      "confidence": 0.9483077526092529
    }
  },
  {
    "text": "long yellow fruit",
    "intent": "clarify",
    "intent_prediction": {
      "name": "pick up",
      "confidence": 0.9593669772148132
    }
  },
  {
    "text": "right",
    "intent": "clarify",
    "intent_prediction": {
      "name": "affirmative",
      "confidence": 0.7161653637886047
    }
  },
  {
    "text": "what i mean is an pink strawberry",
    "intent": "clarify",
    "intent_prediction": {
      "name": "show",
      "confidence": 0.9920347332954407
    }
  },
  {
    "text": "spot blue apple",
    "intent": "find",
    "intent_prediction": {
      "name": "clarify",
      "confidence": 0.9916864037513733
    }
  },
  {
    "text": "what i meant was find this shape which is brown maybe",
    "intent": "find",
    "intent_prediction": {
      "name": "clarify",
      "confidence": 0.7891449332237244
    }
  },
  {
    "text": "could you please pick up the red brick",
    "intent": "move",
    "intent_prediction": {
      "name": "pick up",
      "confidence": 1.0
    }
  },
  {
    "text": "take all the yellow objects and throw them on the ground",
    "intent": "move",
    "intent_prediction": {
      "name": "pick up",
      "confidence": 0.9988723397254944
    }
  },
  {
    "text": "i want you to let go of this object and grab the purple bottle",
    "intent": "move",
    "intent_prediction": {
      "name": "pick up",
      "confidence": 0.9974896907806396
    }
  },
  {
    "text": "i mean place an kiwi that is orange located in the area on the right",
    "intent": "pick up",
    "intent_prediction": {
      "name": "move",
      "confidence": 0.8573420643806458
    }
  },
  {
    "text": "what i meant was get some donut which is magenta thanks",
    "intent": "pick up",
    "intent_prediction": {
      "name": "find",
      "confidence": 0.6556713581085205
    }
  },
  {
    "text": "i wanted to say shift an tomato on the floor",
    "intent": "pick up",
    "intent_prediction": {
      "name": "move",
      "confidence": 0.997920572757721
    }
  },
  {
    "text": "hey could you place the apple on the left",
    "intent": "pick up",
    "intent_prediction": {
      "name": "move",
      "confidence": 0.9970945119857788
    }
  },
  {
    "text": "i'd really like it if you could pick up this yellow cell phone thanks very much",
    "intent": "pick up",
    "intent_prediction": {
      "name": "move",
      "confidence": 0.7689819931983948
    }
  },
  {
    "text": "place the object",
    "intent": "pick up",
    "intent_prediction": {
      "name": "move",
      "confidence": 0.8390111327171326
    }
  },
  {
    "text": "try to balance the apple on the orange",
    "intent": "pick up",
    "intent_prediction": {
      "name": "move",
      "confidence": 0.9886929392814636
    }
  },
  {
    "text": "ok maybe pick up some pink tomato if you can",
    "intent": "pick up",
    "intent_prediction": {
      "name": "find",
      "confidence": 0.7508546113967896
    }
  },
  {
    "text": "please take the green apple and place it in the middle",
    "intent": "pick up",
    "intent_prediction": {
      "name": "move",
      "confidence": 0.99994295835495
    }
  },
  {
    "text": "place this brown pineapple placed at the center",
    "intent": "pick up",
    "intent_prediction": {
      "name": "move",
      "confidence": 0.9998989105224609
    }
  },
  {
    "text": "what i meant was put this magenta shape",
    "intent": "pick up",
    "intent_prediction": {
      "name": "clarify",
      "confidence": 0.6811795234680176
    }
  },
  {
    "text": "positioned in the right zone is that brick of color brown",
    "intent": "show",
    "intent_prediction": {
      "name": "move",
      "confidence": 0.9561704993247986
    }
  },
  {
    "text": "identify and save",
    "intent": "show",
    "intent_prediction": {
      "name": "find",
      "confidence": 0.6165143251419067
    }
  },
  {
    "text": "ok let me show you a cherry",
    "intent": "show",
    "intent_prediction": {
      "name": "find",
      "confidence": 0.9239527583122253
    }
  },
  {
    "text": "hello what do you know how to do",
    "intent": "greetings",
    "intent_prediction": {
      "name": "none",
      "confidence": 0.7588823437690735
    }
  },
  {
    "text": "yes pick it up",
    "intent": "affirmative",
    "intent_prediction": {
      "name": "pick up",
      "confidence": 0.9998413324356079
    }
  },
  {
    "text": "yeah grab it now",
    "intent": "affirmative",
    "intent_prediction": {
      "name": "pick up",
      "confidence": 0.9586449861526489
    }
  },
  {
    "text": "could you pass the turing test if you wanted",
    "intent": "none",
    "intent_prediction": {
      "name": "pick up",
      "confidence": 0.7503807544708252
    }
  },
  {
    "text": "too bad",
    "intent": "none",
    "intent_prediction": {
      "name": "affirmative",
      "confidence": 0.462801992893219
    }
  },
  {
    "text": "dude",
    "intent": "none",
    "intent_prediction": {
      "name": "deny",
      "confidence": 0.35245195031166077
    }
  },
  {
    "text": "which item do you want to smash first",
    "intent": "none",
    "intent_prediction": {
      "name": "pick up",
      "confidence": 0.9031147360801697
    }
  },
  {
    "text": "the violent delights have violent ends",
    "intent": "none",
    "intent_prediction": {
      "name": "move",
      "confidence": 0.7079057693481445
    }
  },
  {
    "text": "leave me alone",
    "intent": "none",
    "intent_prediction": {
      "name": "deny",
      "confidence": 0.7033990621566772
    }
  },
  {
    "text": "fuck off",
    "intent": "none",
    "intent_prediction": {
      "name": "deny",
      "confidence": 0.7633953094482422
    }
  },
  {
    "text": "i would wait for the task to be complete and then ask again",
    "intent": "none",
    "intent_prediction": {
      "name": "deny",
      "confidence": 0.7568857073783875
    }
  },
  {
    "text": "re-program it i guess",
    "intent": "none",
    "intent_prediction": {
      "name": "pick up",
      "confidence": 0.8160009980201721
    }
  },
  {
    "text": "strangle yourself with your arms",
    "intent": "none",
    "intent_prediction": {
      "name": "pick up",
      "confidence": 0.8524446487426758
    }
  },
  {
    "text": "what objects do you know then",
    "intent": "none",
    "intent_prediction": {
      "name": "show",
      "confidence": 0.7038523554801941
    }
  },
  {
    "text": "anytime buddy",
    "intent": "none",
    "intent_prediction": {
      "name": "affirmative",
      "confidence": 0.9225078225135803
    }
  },
  {
    "text": "hey alexa play rock music",
    "intent": "none",
    "intent_prediction": {
      "name": "pick up",
      "confidence": 0.3727976679801941
    }
  },
  {
    "text": "are the fruits ripe",
    "intent": "none",
    "intent_prediction": {
      "name": "pick up",
      "confidence": 0.9708134531974792
    }
  },
  {
    "text": "how does this work exactly",
    "intent": "none",
    "intent_prediction": {
      "name": "affirmative",
      "confidence": 0.637354850769043
    }
  },
  {
    "text": "don't break anything",
    "intent": "none",
    "intent_prediction": {
      "name": "pick up",
      "confidence": 0.8170819282531738
    }
  },
  {
    "text": "ok then what can you do for real",
    "intent": "none",
    "intent_prediction": {
      "name": "find",
      "confidence": 0.8699995279312134
    }
  },
  {
    "text": "thanks",
    "intent": "bye",
    "intent_prediction": {
      "name": "none",
      "confidence": 0.8982944488525391
    }
  },
  {
    "text": "thanks robot that's it for now",
    "intent": "bye",
    "intent_prediction": {
      "name": "affirmative",
      "confidence": 0.5232579112052917
    }
  },
  {
    "text": "till next time",
    "intent": "bye",
    "intent_prediction": {
      "name": "affirmative",
      "confidence": 0.9026645421981812
    }
  },
  {
    "text": "none",
    "intent": "deny",
    "intent_prediction": {
      "name": "affirmative",
      "confidence": 0.5810331702232361
    }
  },
  {
    "text": "annul",
    "intent": "deny",
    "intent_prediction": {
      "name": "show",
      "confidence": 0.3864904046058655
    }
  },
  {
    "text": "you screwed up",
    "intent": "deny",
    "intent_prediction": {
      "name": "pick up",
      "confidence": 0.8347381949424744
    }
  },
  {
    "text": "hey robot undo last job",
    "intent": "deny",
    "intent_prediction": {
      "name": "greetings",
      "confidence": 0.7728928923606873
    }
  },
  {
    "text": "no i wanted you to",
    "intent": "deny",
    "intent_prediction": {
      "name": "clarify",
      "confidence": 0.45363178849220276
    }
  },
  {
    "text": "james undo",
    "intent": "deny",
    "intent_prediction": {
      "name": "show",
      "confidence": 0.6127223968505859
    }
  }
]